selfie_validator/__init__.py
selfie_validator/exceptions.py
selfie_validator/validator.py
selfie_validator-1.0.0.dist-info/METADATA
selfie_validator-1.0.0.dist-info/WHEEL
selfie_validator-1.0.0.dist-info/top_level.txt
selfie_validator-1.0.0.dist-info/RECORD
