Metadata-Version: 2.4
Name: selfie-validator
Version: 1.0.0
Summary: A Python package for validating selfie image quality
Home-page: https://github.com/du2x/selfie-validator
Author: du2x
Author-email: Your Name <your.email@example.com>
License: MIT
Project-URL: Homepage, https://github.com/yourusername/selfie-validator
Project-URL: Bug Tracker, https://github.com/yourusername/selfie-validator/issues
Project-URL: Documentation, https://github.com/yourusername/selfie-validator#readme
Keywords: selfie,image validation,face detection,opencv,computer vision
Classifier: Development Status :: 4 - Beta
Classifier: Intended Audience :: Developers
Classifier: Topic :: Scientific/Engineering :: Image Processing
Classifier: Topic :: Software Development :: Libraries :: Python Modules
Classifier: License :: OSI Approved :: MIT License
Classifier: Programming Language :: Python :: 3
Classifier: Programming Language :: Python :: 3.8
Classifier: Programming Language :: Python :: 3.9
Classifier: Programming Language :: Python :: 3.10
Classifier: Programming Language :: Python :: 3.11
Classifier: Operating System :: OS Independent
Requires-Python: >=3.8
Requires-Dist: opencv-python>=4.5.0
Requires-Dist: numpy>=1.19.0
Requires-Dist: Pillow>=8.0.0
Provides-Extra: dev
Requires-Dist: pytest>=6.0; extra == "dev"
Requires-Dist: pytest-cov>=2.0; extra == "dev"
Requires-Dist: black>=21.0; extra == "dev"
Requires-Dist: flake8>=3.8; extra == "dev"
Requires-Dist: mypy>=0.910; extra == "dev"
Dynamic: author
Dynamic: home-page
Dynamic: requires-python
